[
    {
        "馬": "レアグリフォン",
        "騎手": "横山琉人",
        "馬番": "1",
        "オッズ": "66.3",
        "体重": 472.0,
        "体重変化": 6.0,
        "齢": 4.0,
        "斤量": 58.0,
        "人気": "12",
        "距離": "1200",
        "性": "牡",
        "日付": "2025-01-26",
        "クラス": "４歳以上３勝クラス",
        "芝・ダート": "ダ",
        "回り": "右",
        "馬場": "良",
        "天気": "晴",
        "場名": "中山",
        "race_id": "202506010910",
        "レース名": "江戸川S"
    },
    {
        "馬": "ムーヴ",
        "騎手": "三浦皇成",
        "馬番": "2",
        "オッズ": "4.3",
        "体重": 478.0,
        "体重変化": -4.0,
        "齢": 6.0,
        "斤量": 58.0,
        "人気": null,
        "距離": "1200",
        "性": "牡",
        "日付": "2025-01-26",
        "クラス": "４歳以上３勝クラス",
        "芝・ダート": "ダ",
        "回り": "右",
        "馬場": "良",
        "天気": "晴",
        "場名": "中山",
        "race_id": "202506010910",
        "レース名": "江戸川S"
    },
    {
        "馬": "アイアムユウシュン",
        "騎手": "戸崎圭太",
        "馬番": "3",
        "オッズ": "2.2",
        "体重": 516.0,
        "体重変化": 0.0,
        "齢": 4.0,
        "斤量": 58.0,
        "人気": null,
        "距離": "1200",
        "性": "牡",
        "日付": "2025-01-26",
        "クラス": "４歳以上３勝クラス",
        "芝・ダート": "ダ",
        "回り": "右",
        "馬場": "良",
        "天気": "晴",
        "場名": "中山",
        "race_id": "202506010910",
        "レース名": "江戸川S"
    },
    {
        "馬": "カフジエニアゴン",
        "騎手": "木幡巧也",
        "馬番": "4",
        "オッズ": "228.2",
        "体重": 494.0,
        "体重変化": 0.0,
        "齢": 6.0,
        "斤量": 56.0,
        "人気": "15",
        "距離": "1200",
        "性": "牝",
        "日付": "2025-01-26",
        "クラス": "４歳以上３勝クラス",
        "芝・ダート": "ダ",
        "回り": "右",
        "馬場": "良",
        "天気": "晴",
        "場名": "中山",
        "race_id": "202506010910",
        "レース名": "江戸川S"
    },
    {
        "馬": "ビルカール",
        "騎手": "田辺裕信",
        "馬番": "5",
        "オッズ": "48.4",
        "体重": 478.0,
        "体重変化": 0.0,
        "齢": 5.0,
        "斤量": 58.0,
        "人気": "10",
        "距離": "1200",
        "性": "牡",
        "日付": "2025-01-26",
        "クラス": "４歳以上３勝クラス",
        "芝・ダート": "ダ",
        "回り": "右",
        "馬場": "良",
        "天気": "晴",
        "場名": "中山",
        "race_id": "202506010910",
        "レース名": "江戸川S"
    },
    {
        "馬": "パルデンス",
        "騎手": "内田博幸",
        "馬番": "6",
        "オッズ": "29.5",
        "体重": 498.0,
        "体重変化": -2.0,
        "齢": 7.0,
        "斤量": 58.0,
        "人気": "8",
        "距離": "1200",
        "性": "牡",
        "日付": "2025-01-26",
        "クラス": "４歳以上３勝クラス",
        "芝・ダート": "ダ",
        "回り": "右",
        "馬場": "良",
        "天気": "晴",
        "場名": "中山",
        "race_id": "202506010910",
        "レース名": "江戸川S"
    },
    {
        "馬": "ベンダバリラビア",
        "騎手": "キング",
        "馬番": "7",
        "オッズ": "20.4",
        "体重": 540.0,
        "体重変化": 2.0,
        "齢": 5.0,
        "斤量": 58.0,
        "人気": "6",
        "距離": "1200",
        "性": "牡",
        "日付": "2025-01-26",
        "クラス": "４歳以上３勝クラス",
        "芝・ダート": "ダ",
        "回り": "右",
        "馬場": "良",
        "天気": "晴",
        "場名": "中山",
        "race_id": "202506010910",
        "レース名": "江戸川S"
    },
    {
        "馬": "サザンステート",
        "騎手": "石橋脩",
        "馬番": "8",
        "オッズ": "51.4",
        "体重": 504.0,
        "体重変化": 4.0,
        "齢": 6.0,
        "斤量": 58.0,
        "人気": "11",
        "距離": "1200",
        "性": "牡",
        "日付": "2025-01-26",
        "クラス": "４歳以上３勝クラス",
        "芝・ダート": "ダ",
        "回り": "右",
        "馬場": "良",
        "天気": "晴",
        "場名": "中山",
        "race_id": "202506010910",
        "レース名": "江戸川S"
    },
    {
        "馬": "アシャカタカ",
        "騎手": "横山武史",
        "馬番": "9",
        "オッズ": "12.2",
        "体重": 480.0,
        "体重変化": 8.0,
        "齢": 5.0,
        "斤量": 58.0,
        "人気": "4",
        "距離": "1200",
        "性": "牡",
        "日付": "2025-01-26",
        "クラス": "４歳以上３勝クラス",
        "芝・ダート": "ダ",
        "回り": "右",
        "馬場": "良",
        "天気": "晴",
        "場名": "中山",
        "race_id": "202506010910",
        "レース名": "江戸川S"
    },
    {
        "馬": "コパノハンプトン",
        "騎手": "松岡正海",
        "馬番": "10",
        "オッズ": "27.5",
        "体重": 514.0,
        "体重変化": -4.0,
        "齢": 5.0,
        "斤量": 58.0,
        "人気": "7",
        "距離": "1200",
        "性": "牡",
        "日付": "2025-01-26",
        "クラス": "４歳以上３勝クラス",
        "芝・ダート": "ダ",
        "回り": "右",
        "馬場": "良",
        "天気": "晴",
        "場名": "中山",
        "race_id": "202506010910",
        "レース名": "江戸川S"
    },
    {
        "馬": "オウバイトウリ",
        "騎手": "津村明秀",
        "馬番": "11",
        "オッズ": "4.7",
        "体重": 478.0,
        "体重変化": 0.0,
        "齢": 4.0,
        "斤量": 56.0,
        "人気": null,
        "距離": "1200",
        "性": "牝",
        "日付": "2025-01-26",
        "クラス": "４歳以上３勝クラス",
        "芝・ダート": "ダ",
        "回り": "右",
        "馬場": "良",
        "天気": "晴",
        "場名": "中山",
        "race_id": "202506010910",
        "レース名": "江戸川S"
    },
    {
        "馬": "タイセイブリリオ",
        "騎手": "北村宏司",
        "馬番": "12",
        "オッズ": "18.1",
        "体重": 482.0,
        "体重変化": -2.0,
        "齢": 6.0,
        "斤量": 58.0,
        "人気": "5",
        "距離": "1200",
        "性": "牡",
        "日付": "2025-01-26",
        "クラス": "４歳以上３勝クラス",
        "芝・ダート": "ダ",
        "回り": "右",
        "馬場": "良",
        "天気": "晴",
        "場名": "中山",
        "race_id": "202506010910",
        "レース名": "江戸川S"
    },
    {
        "馬": "ダテボレアス",
        "騎手": "ルメートル",
        "馬番": "13",
        "オッズ": "76.6",
        "体重": 488.0,
        "体重変化": -2.0,
        "齢": 6.0,
        "斤量": 58.0,
        "人気": "13",
        "距離": "1200",
        "性": "牡",
        "日付": "2025-01-26",
        "クラス": "４歳以上３勝クラス",
        "芝・ダート": "ダ",
        "回り": "右",
        "馬場": "良",
        "天気": "晴",
        "場名": "中山",
        "race_id": "202506010910",
        "レース名": "江戸川S"
    },
    {
        "馬": "エメラルドビーチ",
        "騎手": "岩田望来",
        "馬番": "14",
        "オッズ": "38.5",
        "体重": 528.0,
        "体重変化": 0.0,
        "齢": 5.0,
        "斤量": 58.0,
        "人気": "9",
        "距離": "1200",
        "性": "牡",
        "日付": "2025-01-26",
        "クラス": "４歳以上３勝クラス",
        "芝・ダート": "ダ",
        "回り": "右",
        "馬場": "良",
        "天気": "晴",
        "場名": "中山",
        "race_id": "202506010910",
        "レース名": "江戸川S"
    },
    {
        "馬": "ホワイトガーベラ",
        "騎手": "大野拓弥",
        "馬番": "15",
        "オッズ": "85.0",
        "体重": 510.0,
        "体重変化": 10.0,
        "齢": 6.0,
        "斤量": 58.0,
        "人気": "14",
        "距離": "1200",
        "性": "牡",
        "日付": "2025-01-26",
        "クラス": "４歳以上３勝クラス",
        "芝・ダート": "ダ",
        "回り": "右",
        "馬場": "良",
        "天気": "晴",
        "場名": "中山",
        "race_id": "202506010910",
        "レース名": "江戸川S"
    }
]