[
    {
        "馬":"バッファローライズ",
        "騎手":"小林脩斗",
        "馬番":"1",
        "オッズ":"110.6",
        "体重":508.0,
        "体重変化":4.0,
        "齢":4.0,
        "斤量":56.0,
        "人気":"13",
        "距離":"1000",
        "性":"牡",
        "日付":"2025-01-26",
        "クラス":"４歳以上１勝クラス",
        "芝・ダート":"ダ",
        "回り":"右",
        "馬場":"良",
        "天気":"晴",
        "場名":"小倉",
        "race_id":"202510010203",
        "レース名":"4歳以上1勝クラス"
    },
    {
        "馬":"サンディブロンド",
        "騎手":"丸山元気",
        "馬番":"2",
        "オッズ":"5.7",
        "体重":486.0,
        "体重変化":6.0,
        "齢":4.0,
        "斤量":56.0,
        "人気":"3",
        "距離":"1000",
        "性":"牝",
        "日付":"2025-01-26",
        "クラス":"４歳以上１勝クラス",
        "芝・ダート":"ダ",
        "回り":"右",
        "馬場":"良",
        "天気":"晴",
        "場名":"小倉",
        "race_id":"202510010203",
        "レース名":"4歳以上1勝クラス"
    },
    {
        "馬":"アイリッシュパール",
        "騎手":"石神深道",
        "馬番":"3",
        "オッズ":"35.8",
        "体重":480.0,
        "体重変化":0.0,
        "齢":5.0,
        "斤量":53.0,
        "人気":"8",
        "距離":"1000",
        "性":"牝",
        "日付":"2025-01-26",
        "クラス":"４歳以上１勝クラス",
        "芝・ダート":"ダ",
        "回り":"右",
        "馬場":"良",
        "天気":"晴",
        "場名":"小倉",
        "race_id":"202510010203",
        "レース名":"4歳以上1勝クラス"
    },
    {
        "馬":"ミッキースピナッチ",
        "騎手":"池添謙一",
        "馬番":"4",
        "オッズ":"4.0",
        "体重":518.0,
        "体重変化":6.0,
        "齢":5.0,
        "斤量":58.0,
        "人気":"2",
        "距離":"1000",
        "性":"牡",
        "日付":"2025-01-26",
        "クラス":"４歳以上１勝クラス",
        "芝・ダート":"ダ",
        "回り":"右",
        "馬場":"良",
        "天気":"晴",
        "場名":"小倉",
        "race_id":"202510010203",
        "レース名":"4歳以上1勝クラス"
    },
    {
        "馬":"ニシノルミリオン",
        "騎手":"菊沢一樹",
        "馬番":"5",
        "オッズ":"44.2",
        "体重":484.0,
        "体重変化":20.0,
        "齢":4.0,
        "斤量":58.0,
        "人気":"10",
        "距離":"1000",
        "性":"牡",
        "日付":"2025-01-26",
        "クラス":"４歳以上１勝クラス",
        "芝・ダート":"ダ",
        "回り":"右",
        "馬場":"良",
        "天気":"晴",
        "場名":"小倉",
        "race_id":"202510010203",
        "レース名":"4歳以上1勝クラス"
    },
    {
        "馬":"マサレエトワール",
        "騎手":"松本大輝",
        "馬番":"6",
        "オッズ":"5.8",
        "体重":488.0,
        "体重変化":0.0,
        "齢":4.0,
        "斤量":55.0,
        "人気":"5",
        "距離":"1000",
        "性":"牝",
        "日付":"2025-01-26",
        "クラス":"４歳以上１勝クラス",
        "芝・ダート":"ダ",
        "回り":"右",
        "馬場":"良",
        "天気":"晴",
        "場名":"小倉",
        "race_id":"202510010203",
        "レース名":"4歳以上1勝クラス"
    },
    {
        "馬":"サザンレイク",
        "騎手":"佐々木大輔",
        "馬番":"7",
        "オッズ":"39.1",
        "体重":494.0,
        "体重変化":-2.0,
        "齢":5.0,
        "斤量":56.0,
        "人気":"9",
        "距離":"1000",
        "性":"牝",
        "日付":"2025-01-26",
        "クラス":"４歳以上１勝クラス",
        "芝・ダート":"ダ",
        "回り":"右",
        "馬場":"良",
        "天気":"晴",
        "場名":"小倉",
        "race_id":"202510010203",
        "レース名":"4歳以上1勝クラス"
    },
    {
        "馬":"キャンドルベリー",
        "騎手":"川端海翼",
        "馬番":"8",
        "オッズ":"76.5",
        "体重":426.0,
        "体重変化":-6.0,
        "齢":6.0,
        "斤量":53.0,
        "人気":"12",
        "距離":"1000",
        "性":"牝",
        "日付":"2025-01-26",
        "クラス":"４歳以上１勝クラス",
        "芝・ダート":"ダ",
        "回り":"右",
        "馬場":"良",
        "天気":"晴",
        "場名":"小倉",
        "race_id":"202510010203",
        "レース名":"4歳以上1勝クラス"
    },
    {
        "馬":"カップッチョ",
        "騎手":"黛弘人",
        "馬番":"9",
        "オッズ":"30.2",
        "体重":504.0,
        "体重変化":12.0,
        "齢":8.0,
        "斤量":58.0,
        "人気":"7",
        "距離":"1000",
        "性":"牡",
        "日付":"2025-01-26",
        "クラス":"４歳以上１勝クラス",
        "芝・ダート":"ダ",
        "回り":"右",
        "馬場":"良",
        "天気":"晴",
        "場名":"小倉",
        "race_id":"202510010203",
        "レース名":"4歳以上1勝クラス"
    },
    {
        "馬":"シリウス",
        "騎手":"柴田裕一郎",
        "馬番":"10",
        "オッズ":"5.8",
        "体重":466.0,
        "体重変化":8.0,
        "齢":4.0,
        "斤量":55.0,
        "人気":"4",
        "距離":"1000",
        "性":"牡",
        "日付":"2025-01-26",
        "クラス":"４歳以上１勝クラス",
        "芝・ダート":"ダ",
        "回り":"右",
        "馬場":"良",
        "天気":"晴",
        "場名":"小倉",
        "race_id":"202510010203",
        "レース名":"4歳以上1勝クラス"
    },
    {
        "馬":"ケイパブル",
        "騎手":"小林美駒",
        "馬番":"11",
        "オッズ":"70.9",
        "体重":470.0,
        "体重変化":10.0,
        "齢":5.0,
        "斤量":52.0,
        "人気":"11",
        "距離":"1000",
        "性":"牝",
        "日付":"2025-01-26",
        "クラス":"４歳以上１勝クラス",
        "芝・ダート":"ダ",
        "回り":"右",
        "馬場":"良",
        "天気":"晴",
        "場名":"小倉",
        "race_id":"202510010203",
        "レース名":"4歳以上1勝クラス"
    },
    {
        "馬":"ティーラミレス",
        "騎手":"石田拓郎",
        "馬番":"12",
        "オッズ":"14.4",
        "体重":460.0,
        "体重変化":12.0,
        "齢":5.0,
        "斤量":53.0,
        "人気":"6",
        "距離":"1000",
        "性":"牝",
        "日付":"2025-01-26",
        "クラス":"４歳以上１勝クラス",
        "芝・ダート":"ダ",
        "回り":"右",
        "馬場":"良",
        "天気":"晴",
        "場名":"小倉",
        "race_id":"202510010203",
        "レース名":"4歳以上1勝クラス"
    },
    {
        "馬":"スノーホルンロード",
        "騎手":"永島まなみ",
        "馬番":"13",
        "オッズ":"3.7",
        "体重":514.0,
        "体重変化":4.0,
        "齢":6.0,
        "斤量":56.0,
        "人気":"1",
        "距離":"1000",
        "性":"セ",
        "日付":"2025-01-26",
        "クラス":"４歳以上１勝クラス",
        "芝・ダート":"ダ",
        "回り":"右",
        "馬場":"良",
        "天気":"晴",
        "場名":"小倉",
        "race_id":"202510010203",
        "レース名":"4歳以上1勝クラス"
    },
    {
        "馬":"カフジヴィオレッタ",
        "騎手":"国分恭介",
        "馬番":"14",
        "オッズ":"189.2",
        "体重":490.0,
        "体重変化":0.0,
        "齢":7.0,
        "斤量":56.0,
        "人気":"14",
        "距離":"1000",
        "性":"牝",
        "日付":"2025-01-26",
        "クラス":"４歳以上１勝クラス",
        "芝・ダート":"ダ",
        "回り":"右",
        "馬場":"良",
        "天気":"晴",
        "場名":"小倉",
        "race_id":"202510010203",
        "レース名":"4歳以上1勝クラス"
    }
]