[
    {
        "馬": "クヴェレ",
        "騎手": "川端海翼",
        "馬番": "1",
        "オッズ": "215.7",
        "体重": 448.0,
        "体重変化": 0.0,
        "齢": 3.0,
        "斤量": 54.0,
        "人気": "11",
        "距離": "1800",
        "性": "牡",
        "日付": "2024-12-08",
        "クラス": "３歳以上１勝クラス",
        "芝・ダート": "ダ",
        "回り": "左",
        "馬場": "良",
        "天気": "晴",
        "場名": "中京",
        "race_id": "202407040406",
        "レース名": "3歳以上1勝クラス"
    },
    {
        "馬": "サンライズウェーヴ",
        "騎手": "小林脩斗",
        "馬番": "2",
        "オッズ": "109.4",
        "体重": 488.0,
        "体重変化": -6.0,
        "齢": 3.0,
        "斤量": 55.0,
        "人気": "10",
        "距離": "1800",
        "性": "牡",
        "日付": "2024-12-08",
        "クラス": "３歳以上１勝クラス",
        "芝・ダート": "ダ",
        "回り": "左",
        "馬場": "良",
        "天気": "晴",
        "場名": "中京",
        "race_id": "202407040406",
        "レース名": "3歳以上1勝クラス"
    },
    {
        "馬": "リヴァイデント",
        "騎手": "石神深道",
        "馬番": "3",
        "オッズ": "94.5",
        "体重": 406.0,
        "体重変化": 0.0,
        "齢": 3.0,
        "斤量": 52.0,
        "人気": "9",
        "距離": "1800",
        "性": "牝",
        "日付": "2024-12-08",
        "クラス": "３歳以上１勝クラス",
        "芝・ダート": "ダ",
        "回り": "左",
        "馬場": "良",
        "天気": "晴",
        "場名": "中京",
        "race_id": "202407040406",
        "レース名": "3歳以上1勝クラス"
    },
    {
        "馬": "エスオーライジング",
        "騎手": "小沢大仁",
        "馬番": "4",
        "オッズ": "38.2",
        "体重": 468.0,
        "体重変化": -2.0,
        "齢": 3.0,
        "斤量": 56.0,
        "人気": "7",
        "距離": "1800",
        "性": "牡",
        "日付": "2024-12-08",
        "クラス": "３歳以上１勝クラス",
        "芝・ダート": "ダ",
        "回り": "左",
        "馬場": "良",
        "天気": "晴",
        "場名": "中京",
        "race_id": "202407040406",
        "レース名": "3歳以上1勝クラス"
    },
    {
        "馬": "アルプスオジョー",
        "騎手": "長浜鴻緒",
        "馬番": "5",
        "オッズ": "36.2",
        "体重": 510.0,
        "体重変化": 0.0,
        "齢": 3.0,
        "斤量": 52.0,
        "人気": "6",
        "距離": "1800",
        "性": "牝",
        "日付": "2024-12-08",
        "クラス": "３歳以上１勝クラス",
        "芝・ダート": "ダ",
        "回り": "左",
        "馬場": "良",
        "天気": "晴",
        "場名": "中京",
        "race_id": "202407040406",
        "レース名": "3歳以上1勝クラス"
    },
    {
        "馬": "ウヌボレヤサン",
        "騎手": "西塚洸二",
        "馬番": "6",
        "オッズ": "8.0",
        "体重": 420.0,
        "体重変化": -4.0,
        "齢": 3.0,
        "斤量": 56.0,
        "人気": "4",
        "距離": "1800",
        "性": "牡",
        "日付": "2024-12-08",
        "クラス": "３歳以上１勝クラス",
        "芝・ダート": "ダ",
        "回り": "左",
        "馬場": "良",
        "天気": "晴",
        "場名": "中京",
        "race_id": "202407040406",
        "レース名": "3歳以上1勝クラス"
    },
    {
        "馬": "ゼンダンスカイ",
        "騎手": "柴田裕一郎",
        "馬番": "7",
        "オッズ": "2.1",
        "体重": 456.0,
        "体重変化": -8.0,
        "齢": 3.0,
        "斤量": 54.0,
        "人気": "1",
        "距離": "1800",
        "性": "牡",
        "日付": "2024-12-08",
        "クラス": "３歳以上１勝クラス",
        "芝・ダート": "ダ",
        "回り": "左",
        "馬場": "良",
        "天気": "晴",
        "場名": "中京",
        "race_id": "202407040406",
        "レース名": "3歳以上1勝クラス"
    },
    {
        "馬": "レッドクレメンス",
        "騎手": "高杉吏麒",
        "馬番": "8",
        "オッズ": "6.4",
        "体重": 490.0,
        "体重変化": 2.0,
        "齢": 3.0,
        "斤量": 55.0,
        "人気": "3",
        "距離": "1800",
        "性": "牡",
        "日付": "2024-12-08",
        "クラス": "３歳以上１勝クラス",
        "芝・ダート": "ダ",
        "回り": "左",
        "馬場": "良",
        "天気": "晴",
        "場名": "中京",
        "race_id": "202407040406",
        "レース名": "3歳以上1勝クラス"
    },
    {
        "馬": "ロストボール",
        "騎手": "河原田菜々",
        "馬番": "9",
        "オッズ": "58.5",
        "体重": 446.0,
        "体重変化": 8.0,
        "齢": 5.0,
        "斤量": 54.0,
        "人気": "8",
        "距離": "1800",
        "性": "セ",
        "日付": "2024-12-08",
        "クラス": "３歳以上１勝クラス",
        "芝・ダート": "ダ",
        "回り": "左",
        "馬場": "良",
        "天気": "晴",
        "場名": "中京",
        "race_id": "202407040406",
        "レース名": "3歳以上1勝クラス"
    },
    {
        "馬": "ルフトクス",
        "騎手": "亀田温心",
        "馬番": "10",
        "オッズ": "12.2",
        "体重": 458.0,
        "体重変化": -2.0,
        "齢": 3.0,
        "斤量": 55.0,
        "人気": "5",
        "距離": "1800",
        "性": "牝",
        "日付": "2024-12-08",
        "クラス": "３歳以上１勝クラス",
        "芝・ダート": "ダ",
        "回り": "左",
        "馬場": "良",
        "天気": "晴",
        "場名": "中京",
        "race_id": "202407040406",
        "レース名": "3歳以上1勝クラス"
    },
    {
        "馬": "アスクデビューモア",
        "騎手": "今村聖奈",
        "馬番": "11",
        "オッズ": "3.0",
        "体重": 468.0,
        "体重変化": 0.0,
        "齢": 3.0,
        "斤量": 54.0,
        "人気": "2",
        "距離": "1800",
        "性": "牡",
        "日付": "2024-12-08",
        "クラス": "３歳以上１勝クラス",
        "芝・ダート": "ダ",
        "回り": "左",
        "馬場": "良",
        "天気": "晴",
        "場名": "中京",
        "race_id": "202407040406",
        "レース名": "3歳以上1勝クラス"
    }
]