[
    {
        "馬": "ニシノヒナアラレ",
        "騎手": "野中悠太郎",
        "馬番": "1",
        "オッズ": "12.2",
        "体重": 468.0,
        "体重変化": 0.0,
        "齢": 2.0,
        "斤量": 55.0,
        "人気": "4",
        "距離": "1600",
        "性": "牝",
        "日付": "2024-10-20",
        "クラス": "２歳未勝利",
        "芝・ダート": "芝",
        "回り": "左",
        "馬場": "良",
        "天気": "晴",
        "場名": "東京",
        "race_id": "202405040602",
        "レース名": "2歳未勝利"
    },
    {
        "馬": "ラファエラエンゼル",
        "騎手": "丸田恭介",
        "馬番": "2",
        "オッズ": "59.7",
        "体重": 420.0,
        "体重変化": 0.0,
        "齢": 2.0,
        "斤量": 55.0,
        "人気": "7",
        "距離": "1600",
        "性": "牝",
        "日付": "2024-10-20",
        "クラス": "２歳未勝利",
        "芝・ダート": "芝",
        "回り": "左",
        "馬場": "良",
        "天気": "晴",
        "場名": "東京",
        "race_id": "202405040602",
        "レース名": "2歳未勝利"
    },
    {
        "馬": "ステレオプシス",
        "騎手": "原優介",
        "馬番": "3",
        "オッズ": "26.3",
        "体重": 468.0,
        "体重変化": 4.0,
        "齢": 2.0,
        "斤量": 54.0,
        "人気": "6",
        "距離": "1600",
        "性": "牝",
        "日付": "2024-10-20",
        "クラス": "２歳未勝利",
        "芝・ダート": "芝",
        "回り": "左",
        "馬場": "良",
        "天気": "晴",
        "場名": "東京",
        "race_id": "202405040602",
        "レース名": "2歳未勝利"
    },
    {
        "馬": "アズーラ",
        "騎手": "石田拓郎",
        "馬番": "4",
        "オッズ": "155.1",
        "体重": 418.0,
        "体重変化": 0.0,
        "齢": 2.0,
        "斤量": 52.0,
        "人気": "10",
        "距離": "1600",
        "性": "牝",
        "日付": "2024-10-20",
        "クラス": "２歳未勝利",
        "芝・ダート": "芝",
        "回り": "左",
        "馬場": "良",
        "天気": "晴",
        "場名": "東京",
        "race_id": "202405040602",
        "レース名": "2歳未勝利"
    },
    {
        "馬": "ダノンリュラ",
        "騎手": "田辺裕信",
        "馬番": "5",
        "オッズ": "1.5",
        "体重": 454.0,
        "体重変化": 2.0,
        "齢": 2.0,
        "斤量": 55.0,
        "人気": "1",
        "距離": "1600",
        "性": "牝",
        "日付": "2024-10-20",
        "クラス": "２歳未勝利",
        "芝・ダート": "芝",
        "回り": "左",
        "馬場": "良",
        "天気": "晴",
        "場名": "東京",
        "race_id": "202405040602",
        "レース名": "2歳未勝利"
    },
    {
        "馬": "コスモサンブライト",
        "騎手": "木幡巧也",
        "馬番": "6",
        "オッズ": "101.7",
        "体重": 442.0,
        "体重変化": 2.0,
        "齢": 2.0,
        "斤量": 55.0,
        "人気": "9",
        "距離": "1600",
        "性": "牝",
        "日付": "2024-10-20",
        "クラス": "２歳未勝利",
        "芝・ダート": "芝",
        "回り": "左",
        "馬場": "良",
        "天気": "晴",
        "場名": "東京",
        "race_id": "202405040602",
        "レース名": "2歳未勝利"
    },
    {
        "馬": "バレドラパン",
        "騎手": "団野大成",
        "馬番": "7",
        "オッズ": "18.1",
        "体重": 442.0,
        "体重変化": 2.0,
        "齢": 2.0,
        "斤量": 55.0,
        "人気": "5",
        "距離": "1600",
        "性": "牝",
        "日付": "2024-10-20",
        "クラス": "２歳未勝利",
        "芝・ダート": "芝",
        "回り": "左",
        "馬場": "良",
        "天気": "晴",
        "場名": "東京",
        "race_id": "202405040602",
        "レース名": "2歳未勝利"
    },
    {
        "馬": "ブラックティンカー",
        "騎手": "柴田大知",
        "馬番": "8",
        "オッズ": "88.5",
        "体重": 442.0,
        "体重変化": 12.0,
        "齢": 2.0,
        "斤量": 55.0,
        "人気": "8",
        "距離": "1600",
        "性": "牝",
        "日付": "2024-10-20",
        "クラス": "２歳未勝利",
        "芝・ダート": "芝",
        "回り": "左",
        "馬場": "良",
        "天気": "晴",
        "場名": "東京",
        "race_id": "202405040602",
        "レース名": "2歳未勝利"
    },
    {
        "馬": "プリンセスロロ",
        "騎手": "吉田豊",
        "馬番": "9",
        "オッズ": "4.9",
        "体重": 428.0,
        "体重変化": 2.0,
        "齢": 2.0,
        "斤量": 55.0,
        "人気": "2",
        "距離": "1600",
        "性": "牝",
        "日付": "2024-10-20",
        "クラス": "２歳未勝利",
        "芝・ダート": "芝",
        "回り": "左",
        "馬場": "良",
        "天気": "晴",
        "場名": "東京",
        "race_id": "202405040602",
        "レース名": "2歳未勝利"
    },
    {
        "馬": "カリーン",
        "騎手": "石川裕紀人",
        "馬番": "10",
        "オッズ": "5.0",
        "体重": 462.0,
        "体重変化": 10.0,
        "齢": 2.0,
        "斤量": 55.0,
        "人気": "3",
        "距離": "1600",
        "性": "牝",
        "日付": "2024-10-20",
        "クラス": "２歳未勝利",
        "芝・ダート": "芝",
        "回り": "左",
        "馬場": "良",
        "天気": "晴",
        "場名": "東京",
        "race_id": "202405040602",
        "レース名": "2歳未勝利"
    }
]