[
    {
        "馬": "オールマキシマム",
        "騎手": "小林脩斗",
        "馬番": "1",
        "オッズ": "73.1",
        "体重": 456,
        "体重変化": 4,
        "齢": 4,
        "斤量": 56.0,
        "人気": "10",
        "距離": "1800",
        "性": "牝",
        "日付": "2024-11-30",
        "クラス": "３歳以上２勝クラス",
        "芝・ダート": "ダ",
        "回り": "右",
        "馬場": "稍",
        "天気": "晴",
        "場名": "中山",
        "race_id": "202406050110",
        "レース名": "鹿島特別"
    },
    {
        "馬": "サイモンソーラン",
        "騎手": "原優介",
        "馬番": "2",
        "オッズ": "145.3",
        "体重": 484,
        "体重変化": 2,
        "齢": 5,
        "斤量": 58.0,
        "人気": "12",
        "距離": "1800",
        "性": "牡",
        "日付": "2024-11-30",
        "クラス": "３歳以上２勝クラス",
        "芝・ダート": "ダ",
        "回り": "右",
        "馬場": "稍",
        "天気": "晴",
        "場名": "中山",
        "race_id": "202406050110",
        "レース名": "鹿島特別"
    },
    {
        "馬": "トリグラフ",
        "騎手": "大野拓弥",
        "馬番": "3",
        "オッズ": "238.6",
        "体重": 460,
        "体重変化": 6,
        "齢": 5,
        "斤量": 58.0,
        "人気": "14",
        "距離": "1800",
        "性": "牡",
        "日付": "2024-11-30",
        "クラス": "３歳以上２勝クラス",
        "芝・ダート": "ダ",
        "回り": "右",
        "馬場": "稍",
        "天気": "晴",
        "場名": "中山",
        "race_id": "202406050110",
        "レース名": "鹿島特別"
    },
    {
        "馬": "アイファーグローブ",
        "騎手": "野中悠太郎",
        "馬番": "4",
        "オッズ": "73.5",
        "体重": 480,
        "体重変化": 12,
        "齢": 5,
        "斤量": 58.0,
        "人気": "11",
        "距離": "1800",
        "性": "牡",
        "日付": "2024-11-30",
        "クラス": "３歳以上２勝クラス",
        "芝・ダート": "ダ",
        "回り": "右",
        "馬場": "稍",
        "天気": "晴",
        "場名": "中山",
        "race_id": "202406050110",
        "レース名": "鹿島特別"
    },
    {
        "馬": "エリンアキレウス",
        "騎手": "荻野極",
        "馬番": "5",
        "オッズ": "199.5",
        "体重": 534,
        "体重変化": -4,
        "齢": 4,
        "斤量": 58.0,
        "人気": "13",
        "距離": "1800",
        "性": "牡",
        "日付": "2024-11-30",
        "クラス": "３歳以上２勝クラス",
        "芝・ダート": "ダ",
        "回り": "右",
        "馬場": "稍",
        "天気": "晴",
        "場名": "中山",
        "race_id": "202406050110",
        "レース名": "鹿島特別"
    },
    {
        "馬": "タンゴバイラリン",
        "騎手": "田辺裕信",
        "馬番": "6",
        "オッズ": "4.9",
        "体重": 512,
        "体重変化": 6,
        "齢": 3,
        "斤量": 56.0,
        "人気": "3",
        "距離": "1800",
        "性": "牡",
        "日付": "2024-11-30",
        "クラス": "３歳以上２勝クラス",
        "芝・ダート": "ダ",
        "回り": "右",
        "馬場": "稍",
        "天気": "晴",
        "場名": "中山",
        "race_id": "202406050110",
        "レース名": "鹿島特別"
    },
    {
        "馬": "メジャーデビュー",
        "騎手": "内田博幸",
        "馬番": "7",
        "オッズ": "5.3",
        "体重": 438,
        "体重変化": 8,
        "齢": 3,
        "斤量": 54.0,
        "人気": "4",
        "距離": "1800",
        "性": "牝",
        "日付": "2024-11-30",
        "クラス": "３歳以上２勝クラス",
        "芝・ダート": "ダ",
        "回り": "右",
        "馬場": "稍",
        "天気": "晴",
        "場名": "中山",
        "race_id": "202406050110",
        "レース名": "鹿島特別"
    },
    {
        "馬": "エクストラノート",
        "騎手": "菊沢一樹",
        "馬番": "8",
        "オッズ": "310.4",
        "体重": 480,
        "体重変化": 4,
        "齢": 7,
        "斤量": 58.0,
        "人気": "15",
        "距離": "1800",
        "性": "セ",
        "日付": "2024-11-30",
        "クラス": "３歳以上２勝クラス",
        "芝・ダート": "ダ",
        "回り": "右",
        "馬場": "稍",
        "天気": "晴",
        "場名": "中山",
        "race_id": "202406050110",
        "レース名": "鹿島特別"
    },
    {
        "馬": "サクラトップリアル",
        "騎手": "横山武史",
        "馬番": "9",
        "オッズ": "3.4",
        "体重": 514,
        "体重変化": -2,
        "齢": 3,
        "斤量": 56.0,
        "人気": "1",
        "距離": "1800",
        "性": "牡",
        "日付": "2024-11-30",
        "クラス": "３歳以上２勝クラス",
        "芝・ダート": "ダ",
        "回り": "右",
        "馬場": "稍",
        "天気": "晴",
        "場名": "中山",
        "race_id": "202406050110",
        "レース名": "鹿島特別"
    }
]